Metadata-Version: 1.0
Name: data-distributions-Gauss-binom
Version: 0.1
Summary: Gaussian and binomial distributions
Home-page: UNKNOWN
Author: Niranjan P Salimath
Author-email: niranjanps073@gmail.com
License: UNKNOWN
Platform: UNKNOWN
